pypgq
